craftable/__init__.py
craftable/craftable.py
craftable/adapters/README.md
craftable/adapters/__init__.py
craftable/adapters/from_dataclasses.py
craftable/adapters/from_dataframe.py
craftable/adapters/from_dicts.py
craftable/adapters/from_mapping_of_lists.py
craftable/adapters/from_models.py
craftable/adapters/from_numpy.py
craftable/adapters/from_records.py
craftable/adapters/from_sql.py
craftable/styles/__init__.py
craftable/styles/ascii_style.py
craftable/styles/basic_screen_style.py
craftable/styles/box_chars.py
craftable/styles/docx_style.py
craftable/styles/markdown_style.py
craftable/styles/no_border_screen_style.py
craftable/styles/ods_style.py
craftable/styles/odt_style.py
craftable/styles/rounded_border_screen_style.py
craftable/styles/rtf_style.py
craftable/styles/table_style.py
craftable/styles/xlsx_style.py
craftable-0.2.1.dist-info/METADATA
craftable-0.2.1.dist-info/WHEEL
craftable-0.2.1.dist-info/RECORD
