Metadata-Version: 2.4
Name: craftable
Version: 0.2.1
Summary: craftable - craft elegant tables using format strings
Project-URL: homepage, https://ptyork.github.io/craftable
Project-URL: repository, https://github.com/ptyork/craftable
Project-URL: Bug Tracker, https://github.com/ptyork/craftable/issues
Author-email: Paul York <paul@yorkfamily.com>
License-Expression: MIT
Keywords: craftable,f-string,formatting,grid,pretty,table,terminal
Requires-Python: >=3.10
